CHANGES
COPYING
MANIFEST.in
README
gabi.py
setup.py
gabi.egg-info/PKG-INFO
gabi.egg-info/SOURCES.txt
gabi.egg-info/dependency_links.txt
gabi.egg-info/entry_points.txt
gabi.egg-info/not-zip-safe
gabi.egg-info/requires.txt
gabi.egg-info/top_level.txt