Metadata-Version: 1.0
Name: gabi
Version: 0.1.0
Summary: Google Address Book Importer
Home-page: http://bitbucket.org/lgs/gabi/
Author: Lorenzo Gil Sanchez
Author-email: lorenzo.gil.sanchez@gmail.com
License: GPL 3
Keywords: email google mutt backup
Platform: UNKNOWN
Classifier: Development Status :: 1 - Planning
Classifier: Environment :: Console
Classifier: Intended Audience :: End Users/Desktop
Classifier: License :: OSI Approved :: GNU General Public License (GPL)
Classifier: Operating System :: POSIX
Classifier: Programming Language :: Python
Classifier: Topic :: Utilities
